statecrumbs/__init__.py
statecrumbs/config.py
statecrumbs/context.py
statecrumbs/core.py
statecrumbs/crash.py
statecrumbs/export.py
statecrumbs/formatter.py
statecrumbs-0.1.2.dist-info/licenses/LICENSE
statecrumbs-0.1.2.dist-info/METADATA
statecrumbs-0.1.2.dist-info/WHEEL
statecrumbs-0.1.2.dist-info/top_level.txt
statecrumbs-0.1.2.dist-info/RECORD
