Metadata-Version: 2.4
Name: statecrumbs
Version: 0.1.2
Summary: Lightweight state breadcrumb tracking with context propagation
Author: Hemapriya
License: MIT
Project-URL: Homepage, https://github.com/Nhemapriya/statecrumbs
Project-URL: Source, https://github.com/Nhemapriya/statecrumbs
Project-URL: Issues, https://github.com/Nhemapriya/statecrumbs/issues
Keywords: debugging,observability,state,context,breadcrumbs
Classifier: Programming Language :: Python :: 3
Classifier: License :: OSI Approved :: MIT License
Classifier: Operating System :: OS Independent
Requires-Python: >=3.8
License-File: LICENSE
Dynamic: license-file
